Metadata-Version: 1.0
Name: discrete-distrib
Version: 0.1
Summary: Gaussian Distributions and Binomial Distributions
Home-page: UNKNOWN
Author: Patrick Jose Roxas
Author-email: pjcroxas@neu.edu.ph
License: UNKNOWN
Platform: UNKNOWN
